sleep_models/__init__.py
sleep_models/_version.py
sleep_models/constants.py
sleep_models/explain.py
sleep_models/signature.py
sleep_models/bin/__init__.py
sleep_models/bin/explain.py
sleep_models/bin/get_marker_genes.py
sleep_models/bin/make_dataset.py
sleep_models/bin/make_matrixplot.py
sleep_models/bin/make_umapplot.py
sleep_models/bin/predict.py
sleep_models/bin/remove_marker_genes.py
sleep_models/bin/sweep.py
sleep_models/bin/test_torch_model.py
sleep_models/bin/train_model.py
sleep_models/bin/train_torch_model.py
sleep_models/dimensionality_reduction/__init__.py
sleep_models/dimensionality_reduction/algorithms.py
sleep_models/dimensionality_reduction/dimensionality_reduction.py
sleep_models/models/__init__.py
sleep_models/models/core.py
sleep_models/models/train.py
sleep_models/models/variables.py
sleep_models/models/models/__init__.py
sleep_models/models/models/knn.py
sleep_models/models/models/mlp.py
sleep_models/models/models/models.py
sleep_models/models/models/rf.py
sleep_models/models/models/ebm/__init__.py
sleep_models/models/models/ebm/classifier.py
sleep_models/models/models/ebm/regressor.py
sleep_models/models/torch/__init__.py
sleep_models/models/torch/data.py
sleep_models/models/torch/nn.py
sleep_models/models/torch/test.py
sleep_models/models/torch/tools.py
sleep_models/models/torch/train.py
sleep_models/models/utils/__init__.py
sleep_models/models/utils/config.py
sleep_models/models/utils/eval.py
sleep_models/models/utils/metrics.py
sleep_models/models/utils/plotting.py
sleep_models/models/utils/torch.py
sleep_models/plotting/__init__.py
sleep_models/plotting/plotting.py
sleep_models/plotting/seaborn.py
sleep_models/predict/__init__.py
sleep_models/predict/predict.py
sleep_models/preprocessing/__init__.py
sleep_models/preprocessing/preprocessing.py
sleep_models/tests/__init__.py
sleep_models/tests/test_dimensionality_reduction.py
sleep_models/tests/test_make-matrixplot.py
sleep_models/tests/test_preprocessing.py
sleep_models-2.0.0.dist-info/METADATA
sleep_models-2.0.0.dist-info/WHEEL
sleep_models-2.0.0.dist-info/entry_points.txt
sleep_models-2.0.0.dist-info/top_level.txt
sleep_models-2.0.0.dist-info/RECORD
